spikewidgets/__init__.py
spikewidgets/version.py
spikewidgets/widgets/__init__.py
spikewidgets/widgets/basewidget.py
spikewidgets/widgets/utils.py
spikewidgets/widgets/agreementmatrixwidget/__init__.py
spikewidgets/widgets/agreementmatrixwidget/agreementmatrixwidget.py
spikewidgets/widgets/amplitudewidget/__init__.py
spikewidgets/widgets/amplitudewidget/amplitudewidget.py
spikewidgets/widgets/collisioncompwidget/__init__.py
spikewidgets/widgets/collisioncompwidget/collisioncompwidget.py
spikewidgets/widgets/confusionmatrixwidget/__init__.py
spikewidgets/widgets/confusionmatrixwidget/confusionmatrixwidget.py
spikewidgets/widgets/correlogramswidget/__init__.py
spikewidgets/widgets/correlogramswidget/correlograms_phy.py
spikewidgets/widgets/correlogramswidget/correlogramswidget.py
spikewidgets/widgets/electrodegeometrywidget/__init__.py
spikewidgets/widgets/electrodegeometrywidget/electrodegeometrywidget.py
spikewidgets/widgets/featurewidgets/__init__.py
spikewidgets/widgets/featurewidgets/pcawidget.py
spikewidgets/widgets/isidistwidget/__init__.py
spikewidgets/widgets/isidistwidget/isidistwidget.py
spikewidgets/widgets/mapswidget/__init__.py
spikewidgets/widgets/mapswidget/activitymapwidget.py
spikewidgets/widgets/mapswidget/templatemapswidget.py
spikewidgets/widgets/multicompgraphwidget/__init__.py
spikewidgets/widgets/multicompgraphwidget/multicompgraphwidget.py
spikewidgets/widgets/rasterswidget/__init__.py
spikewidgets/widgets/rasterswidget/rasterswidget.py
spikewidgets/widgets/sortingperformancewidget/__init__.py
spikewidgets/widgets/sortingperformancewidget/sortingperformancewidget.py
spikewidgets/widgets/spectrumwidget/__init__.py
spikewidgets/widgets/spectrumwidget/spectrumwidget.py
spikewidgets/widgets/timeserieswidget/__init__.py
spikewidgets/widgets/timeserieswidget/timeserieswidget.py
spikewidgets/widgets/unitwaveformswidget/__init__.py
spikewidgets/widgets/unitwaveformswidget/unitwaveformswidget.py
spikewidgets-0.5.4.dist-info/LICENSE
spikewidgets-0.5.4.dist-info/METADATA
spikewidgets-0.5.4.dist-info/WHEEL
spikewidgets-0.5.4.dist-info/top_level.txt
spikewidgets-0.5.4.dist-info/RECORD
