Metadata-Version: 2.1
Name: spikewidgets
Version: 0.5.4
Summary: Python widgets for spike sorting and electrophysiology
Home-page: https://github.com/SpikeInterface/spikewidgets
Author: Alessio Buccino, Cole Hurwitz, Samuel Garcia, Jeremy Magland, Matthias Hennig
Author-email: jmagland@flatironinstitute.org
License: UNKNOWN
Platform: UNKNOWN
Classifier: Programming Language :: Python :: 3
Classifier: License :: OSI Approved :: Apache Software License
Classifier: Operating System :: OS Independent
Requires-Dist: numpy
Requires-Dist: spikeextractors (>=0.9.7)
Requires-Dist: spiketoolkit (>=0.7.6)
Requires-Dist: spikecomparison (>=0.3.3)
Requires-Dist: matplotlib
Requires-Dist: MEAutility (>=1.4.8)
